client/__init__.py
client/api_client.py
client/configuration.py
client/rest.py
client/api/__init__.py
client/api/api_proxy_api.py
client/api/application_api.py
client/api/application_api_key_api.py
client/api/application_integration_api.py
client/api/auth_api.py
client/api/category_api.py
client/api/integration_api.py
client/api/statistics_api.py
client/api/tenant_api.py
client/models/__init__.py
client/models/add_integration_to_application_error.py
client/models/add_integration_to_application_request.py
client/models/add_integration_to_application_request_dto.py
client/models/add_integration_to_application_request_error_codes.py
client/models/add_integration_to_application_response.py
client/models/all_of_add_integration_to_application_error_code.py
client/models/all_of_add_integration_to_application_error_type.py
client/models/all_of_add_integration_to_application_request_dto.py
client/models/all_of_add_integration_to_application_response_error.py
client/models/all_of_application_api_key_by_application_id_error_code.py
client/models/all_of_application_api_key_by_application_id_error_type.py
client/models/all_of_application_api_key_by_application_id_response_data.py
client/models/all_of_application_api_key_by_application_id_response_error.py
client/models/all_of_application_integration_dto_application.py
client/models/all_of_application_integration_dto_integration.py
client/models/all_of_application_integration_list_by_application_id_error_code.py
client/models/all_of_application_integration_list_by_application_id_error_type.py
client/models/all_of_application_integration_list_by_application_id_response_data.py
client/models/all_of_application_integration_list_by_application_id_response_error.py
client/models/all_of_call_action_error_code.py
client/models/all_of_call_action_error_type.py
client/models/all_of_call_action_response_data.py
client/models/all_of_call_action_response_error.py
client/models/all_of_category_list_error_code.py
terapi_global_client-1.0.0.dist-info/METADATA
terapi_global_client-1.0.0.dist-info/WHEEL
terapi_global_client-1.0.0.dist-info/top_level.txt
terapi_global_client-1.0.0.dist-info/RECORD
