Metadata-Version: 2.1
Name: terapi-global-client
Version: 1.0.0
Summary: A Python client to easily integrate all Terapi Global services into your application.
Author: Terapi Global
Author-email: integrations@terapi.global
Classifier: Programming Language :: Python :: 3
Classifier: License :: OSI Approved :: MIT License
Classifier: Intended Audience :: Developers
Classifier: Topic :: Software Development :: Libraries :: Python Modules
Requires-Python: >=3.6
